{
    "page": 1,
    "results": [
      {
        "adult": false,
        "backdrop_path": "/gsQJOfeW45KLiQeEIsom94QPQwb.jpg",
        "genre_ids": [
          28,
          53
        ],
        "id": 1125899,
        "original_language": "en",
        "original_title": "Cleaner",
        "overview": "Cuando un grupo de activistas radicales se apodera de la gala anual de una empresa energética y toma 300 rehenes, una ex soldado convertida en limpiacristales suspendida 50 pisos en el exterior del edificio debe salvar a los que están atrapados dentro, incluido su hermano pequeño.",
        "popularity": 547.0493,
        "poster_path": "/2KIqFpvjVI6mNBTQw7MYZdzRYvs.jpg",
        "release_date": "2025-02-19",
        "title": "Cleaner",
        "video": false,
        "vote_average": 6.658,
        "vote_count": 117
      },
      {
        "adult": false,
        "backdrop_path": "/m2mzlsJjE3UAqeUB5fLUkpWg4Iq.jpg",
        "genre_ids": [
          53,
          878
        ],
        "id": 1165067,
        "original_language": "en",
        "original_title": "Cosmic Chaos",
        "overview": "",
        "popularity": 508.2923,
        "poster_path": "/mClzWv7gBqgXfjZXp49Enyoex1v.jpg",
        "release_date": "2023-08-03",
        "title": "Cosmic Chaos",
        "video": false,
        "vote_average": 5.735,
        "vote_count": 17
      },
      {
        "adult": false,
        "backdrop_path": "/8eifdha9GQeZAkexgtD45546XKx.jpg",
        "genre_ids": [
          28,
          53,
          878
        ],
        "id": 822119,
        "original_language": "en",
        "original_title": "Captain America: Brave New World",
        "overview": "Tras reunirse con el recientemente electo presidente de los Estados Unidos Thaddeus Ross, Sam se encuentra en medio de un conflicto internacional. Debe descubrir la razón de un nefasto complot mundial antes de que el verdadero artífice detrás del mismo haga que el mundo entero entre en caos.",
        "popularity": 425.1221,
        "poster_path": "/im71UJzBqY03swuGYVR28j0JFM2.jpg",
        "release_date": "2025-02-13",
        "title": "Capitán América: Un nuevo mundo",
        "video": false,
        "vote_average": 6.1,
        "vote_count": 1154
      },
      {
        "adult": false,
        "backdrop_path": "/ibF5XVxTzf1ayzZrmiJqgeQ39Qk.jpg",
        "genre_ids": [
          28,
          10752
        ],
        "id": 1373723,
        "original_language": "en",
        "original_title": "The Codes of War",
        "overview": "",
        "popularity": 416.471,
        "poster_path": "/oXeiQAfRK90pxxhP5iKPXQqAIN1.jpg",
        "release_date": "2025-03-20",
        "title": "The Codes of War",
        "video": false,
        "vote_average": 6.542,
        "vote_count": 12
      },
      {
        "adult": false,
        "backdrop_path": "/is9bmV6uYXu7LjZGJczxrjJDlv8.jpg",
        "genre_ids": [
          28,
          12
        ],
        "id": 1229730,
        "original_language": "fr",
        "original_title": "Carjackers",
        "overview": "De día, son invisibles: valets, recepcionistas y bármanes de un lujoso hotel. De noche, son los Criminales de lujo, un equipo de conductores que roba a los huéspedes ricos en el camino. Mientras planean su último golpe, la directora del hotel contrata a un cruel asesino para detenerlos a cualquier costo. Con el peligro tan cerca, ¿podrán Nora, Zoé, Steve y Prestance tener éxito con su mayor robo?",
        "popularity": 398.4515,
        "poster_path": "/rpAbueORafYSgTk2oSc2t6ayktb.jpg",
        "release_date": "2025-03-27",
        "title": "Criminales de lujo",
        "video": false,
        "vote_average": 6.8,
        "vote_count": 21
      },
      {
        "adult": false,
        "backdrop_path": "/9OO6I25MHhCDd0XwNk4oZl0fpwB.jpg",
        "genre_ids": [
          28,
          18
        ],
        "id": 1261050,
        "original_language": "da",
        "original_title": "De lydløse",
        "overview": "",
        "popularity": 342.887,
        "poster_path": "/3qHoQfLwK3ZDB9gqse87HBZ5aUD.jpg",
        "release_date": "2024-10-31",
        "title": "De lydløse",
        "video": false,
        "vote_average": 4.8,
        "vote_count": 9
      },
      {
        "adult": false,
        "backdrop_path": "/fTrQsdMS2MUw00RnzH0r3JWHhts.jpg",
        "genre_ids": [
          28,
          80,
          53
        ],
        "id": 1197306,
        "original_language": "en",
        "original_title": "A Working Man",
        "overview": "Levon Cade dejó atrás una distinguida carrera militar en operaciones encubiertas para llevar una vida sencilla trabajando en la construcción. Pero cuando la hija de su jefe, quien es como familia para él, es capturada por traficantes de personas, su búsqueda para traerla de regreso revela un mundo de corrupción mucho mayor de lo que jamás pudo imaginar.",
        "popularity": 266.2088,
        "poster_path": "/aG50Ad3UV8cCQWpNWSHHUqgKGNB.jpg",
        "release_date": "2025-03-27",
        "title": "Rescate implacable",
        "video": false,
        "vote_average": 6.8,
        "vote_count": 58
      },
      {
        "adult": false,
        "backdrop_path": "/xkjWiRQtrenqGRWO2Enry2JIl4d.jpg",
        "genre_ids": [
          27
        ],
        "id": 1388366,
        "original_language": "en",
        "original_title": "Popeye the Slayer Man",
        "overview": "Un curioso grupo de amigos se cuela en una fábrica de conservas de espinacas abandonada para investigar la leyenda del \"Hombre Marinero\", del que se dice que ronda la fábrica y los muelles locales.",
        "popularity": 262.666,
        "poster_path": "/nVwu3mN7hr1yF467pGct3yQFM41.jpg",
        "release_date": "2025-03-21",
        "title": "Popeye the Slayer Man",
        "video": false,
        "vote_average": 6.2,
        "vote_count": 29
      },
      {
        "adult": false,
        "backdrop_path": "/u7j9GwAzEuDmYikzhMDWC9kCAiG.jpg",
        "genre_ids": [
          10751,
          14
        ],
        "id": 447273,
        "original_language": "en",
        "original_title": "Snow White",
        "overview": "Una adaptación en vivo del clásico cuento de hadas sobre una hermosa joven princesa que, mientras es acosada por una reina celosa, busca refugio en la casa de siete enanos en la campiña alemana.",
        "popularity": 258.1002,
        "poster_path": "/dtoWK3K5e9b7gL9tKYMMavqcZxr.jpg",
        "release_date": "2025-03-20",
        "title": "Blanca Nieves",
        "video": false,
        "vote_average": 4.4,
        "vote_count": 432
      },
      {
        "adult": false,
        "backdrop_path": "/1w8kutrRucTd3wlYyu5QlUDMiG1.jpg",
        "genre_ids": [
          12,
          10751,
          16
        ],
        "id": 762509,
        "original_language": "en",
        "original_title": "Mufasa: The Lion King",
        "overview": "Mufasa era un cachorro huérfano, perdido y solo hasta que conoce a un simpático león llamado Taka, heredero de un linaje real. Este encuentro casual pone en marcha un viaje de un extraordinario grupo de inadaptados que buscan su destino.",
        "popularity": 238.3487,
        "poster_path": "/dmw74cWIEKaEgl5Dv3kUTcCob6D.jpg",
        "release_date": "2024-12-19",
        "title": "Mufasa: El rey león",
        "video": false,
        "vote_average": 7.5,
        "vote_count": 1806
      },
      {
        "adult": false,
        "backdrop_path": "/zo8CIjJ2nfNOevqNajwMRO6Hwka.jpg",
        "genre_ids": [
          16,
          12,
          10751,
          35
        ],
        "id": 1241982,
        "original_language": "en",
        "original_title": "Moana 2",
        "overview": "Después de recibir una llamada inesperada de sus antepasados ​​navegantes, Moana viajará a los lejanos mares de Oceanía, donde vivirá una peligrosa aventura con su nueva tripulación.",
        "popularity": 220.0556,
        "poster_path": "/b1WsCRfomw7tRi12NuseKsAJxYK.jpg",
        "release_date": "2024-11-28",
        "title": "Moana 2",
        "video": false,
        "vote_average": 7.1,
        "vote_count": 2104
      },
      {
        "adult": false,
        "backdrop_path": "/3xN4vNPWBSVDsiiOzL5sB95Sa1J.jpg",
        "genre_ids": [
          53,
          9648
        ],
        "id": 257094,
        "original_language": "en",
        "original_title": "Holland",
        "overview": "Nancy Vandergroot, una profesora y ama de casa de vida aparentemente perfecta de Holland, Míchigan, comienza a sospechar de que su marido la está engañando, y se involucra en una aventura por su cuenta antes de enterarse de su verdadera y oscura vida secreta",
        "popularity": 214.0209,
        "poster_path": "/39jIr3A4ScUeGxFdMeARYKNxTgU.jpg",
        "release_date": "2025-03-27",
        "title": "Holland",
        "video": false,
        "vote_average": 5.525,
        "vote_count": 118
      },
      {
        "adult": false,
        "backdrop_path": "/e807jDKiFcntZS32ze88X6I96OD.jpg",
        "genre_ids": [
          16,
          28
        ],
        "id": 1297763,
        "original_language": "ja",
        "original_title": "ニンジャバットマン対ヤクザリーグ",
        "overview": "Sólo un día después de regresar del pasado, Batman y sus aliados descubren que el mundo no es exactamente el mismo que dejaron. Toda la isla de Japón ya no existe y los héroes de la Liga de la Justicia tampoco. Pero antes de que puedan comprender lo que está pasando, los yakuza empiezan a llover literalmente del cielo. Secuela de la película anime 3D \"Batman Ninja\"",
        "popularity": 175.1912,
        "poster_path": "/3hVjnB5FE4gBrR5rqk42qiBFgGe.jpg",
        "release_date": "2025-03-17",
        "title": "Batman Ninja vs La Liga Yakuza",
        "video": false,
        "vote_average": 6.811,
        "vote_count": 95
      },
      {
        "adult": false,
        "backdrop_path": "/deUWVEgNh2IGjShyymZhaYP40ye.jpg",
        "genre_ids": [
          28,
          12,
          53
        ],
        "id": 1356039,
        "original_language": "es",
        "original_title": "Contraataque",
        "overview": "Tras rescatar a dos rehenes y hacerse de un nuevo enemigo, el capitán Guerrero y su escuadrón de élite se enfrentan a la emboscada de un grupo criminal.",
        "popularity": 171.7411,
        "poster_path": "/kxnFdLJhi37ZVFDCL1ka0yeQVU5.jpg",
        "release_date": "2025-02-28",
        "title": "Contraataque",
        "video": false,
        "vote_average": 8.4,
        "vote_count": 573
      },
      {
        "adult": false,
        "backdrop_path": "/sulUXRukzh7WSK34y8mnaUcHo3y.jpg",
        "genre_ids": [
          10749,
          35,
          18
        ],
        "id": 1254786,
        "original_language": "en",
        "original_title": "The Life List",
        "overview": "A pedido de su madre, una mujer se dispone a cumplir los deseos de su adolescencia. En el camino, desentraña secretos familiares, encuentra el amor y se redescubre a sí misma.",
        "popularity": 171.316,
        "poster_path": "/r6K6spYEWf7aDGsY4EdkScZW1Hl.jpg",
        "release_date": "2025-03-28",
        "title": "Mi lista de deseos",
        "video": false,
        "vote_average": 6.9,
        "vote_count": 77
      },
      {
        "adult": false,
        "backdrop_path": "/19pr5CzgsBYs67FAJvke8GQxN4g.jpg",
        "genre_ids": [
          27
        ],
        "id": 1301650,
        "original_language": "mn",
        "original_title": "Z Zone",
        "overview": "Un grupo de jóvenes delincuentes, trasladados a una remota base militar para su rehabilitación, se ven atrapados en una red de secretos y luchan contra fuerzas siniestras que acechan en las sombras.",
        "popularity": 170.6283,
        "poster_path": "/ynW7ZFLZsbVQozvzdAOLdQrLL9P.jpg",
        "release_date": "2025-02-07",
        "title": "Z Zone",
        "video": false,
        "vote_average": 7.1,
        "vote_count": 14
      },
      {
        "adult": false,
        "backdrop_path": "/gFFqWsjLjRfipKzlzaYPD097FNC.jpg",
        "genre_ids": [
          28,
          80,
          53
        ],
        "id": 1126166,
        "original_language": "en",
        "original_title": "Flight Risk",
        "overview": "Un piloto transporta a un alguacil del aire que acompaña a un fugitivo a juicio. A medida que atraviesan el desierto de Alaska, la tensión aumenta y la confianza se pone a prueba, ya que no todos a bordo son quienes parecen.",
        "popularity": 156.0759,
        "poster_path": "/8T6nkYb4W8BIeafmFffyfsRciTL.jpg",
        "release_date": "2025-01-30",
        "title": "Amenaza en el aire",
        "video": false,
        "vote_average": 6.159,
        "vote_count": 558
      },
      {
        "adult": false,
        "backdrop_path": "/zOpe0eHsq0A2NvNyBbtT6sj53qV.jpg",
        "genre_ids": [
          28,
          878,
          35,
          10751,
          12,
          14
        ],
        "id": 939243,
        "original_language": "en",
        "original_title": "Sonic the Hedgehog 3",
        "overview": "Sonic, Knuckles y Tails se reúnen para enfrentarse a un nuevo y poderoso adversario, Shadow, un misterioso villano con poderes nunca antes vistos. Con sus habilidades superadas en todos los sentidos, el Equipo Sonic debe buscar una alianza improbable con la esperanza de detener a Shadow y proteger el planeta.",
        "popularity": 150.0364,
        "poster_path": "/3aDWCRXLYOCuxjrjiPfLd79tcI6.jpg",
        "release_date": "2024-12-25",
        "title": "Sonic 3: La Película",
        "video": false,
        "vote_average": 7.8,
        "vote_count": 2301
      },
      {
        "adult": false,
        "backdrop_path": "/9nhjGaFLKtddDPtPaX5EmKqsWdH.jpg",
        "genre_ids": [
          10749,
          878,
          53
        ],
        "id": 950396,
        "original_language": "en",
        "original_title": "The Gorge",
        "overview": "Dos agentes altamente entrenados se unen a la distancia tras ser enviados a proteger bordes opuestos de un abismo misterioso. Cuando la maldad emerge de él, tienen que trabajar juntos para sobrevivir a lo que yace dentro del abismo.",
        "popularity": 140.8421,
        "poster_path": "/3s0jkMh0YUhIeIeioH3kt2X4st4.jpg",
        "release_date": "2025-02-13",
        "title": "El abismo secreto",
        "video": false,
        "vote_average": 7.7,
        "vote_count": 2201
      },
      {
        "adult": false,
        "backdrop_path": "/99XoA625Gl9Q5tBKGX1nf2g11yJ.jpg",
        "genre_ids": [
          27,
          14
        ],
        "id": 1139937,
        "original_language": "en",
        "original_title": "Frogman",
        "overview": "Tres amigos en busca del Hombre Rana descubren que es algo más que una leyenda local.",
        "popularity": 132.9766,
        "poster_path": "/wFCM4SKsBQIpKXhcCGgkVf7DK2F.jpg",
        "release_date": "2024-09-26",
        "title": "Frogman",
        "video": false,
        "vote_average": 5,
        "vote_count": 9
      }
    ],
    "total_pages": 49485,
    "total_results": 989695
  }